s3_pull_processor/__init__.py
s3_pull_processor/actions.py
s3_pull_processor/artifact.py
s3_pull_processor/aws.py
s3_pull_processor/pull.py
s3_pull_processor/s3_pull_processor.py
s3_pull_processor/upload.py
s3_pull_processor/util.py
test/__init__.py
test/test_e2e.py
test/test_s3_files.py
test/test_sqs_messages.py
test/test_wipe_out.py
s3_pull_processor-0.3.dist-info/LICENSE
s3_pull_processor-0.3.dist-info/METADATA
s3_pull_processor-0.3.dist-info/WHEEL
s3_pull_processor-0.3.dist-info/entry_points.txt
s3_pull_processor-0.3.dist-info/top_level.txt
s3_pull_processor-0.3.dist-info/RECORD
