Metadata-Version: 2.1
Name: s3-pull-processor
Version: 0.3
Summary: A cli to upload and retrieve data to/from S3 object storage and processing data running actions on it.
Author: Eduardo Cerqueira
License: UNKNOWN
Platform: UNKNOWN
Requires-Python: >=3.6
License-File: LICENSE
Requires-Dist: click
Requires-Dist: pytest
Requires-Dist: boto3
Provides-Extra: dev
Requires-Dist: flake8 ; extra == 'dev'
Requires-Dist: pylint ; extra == 'dev'
Requires-Dist: pre-commit ; extra == 'dev'
Requires-Dist: pytest ; extra == 'dev'
Requires-Dist: twine ; extra == 'dev'
